{
  "project_info": {
    "project_number": "764934368349",
    "firebase_url": "https://clubssocsdcu.firebaseio.com",
    "project_id": "clubssocsdcu",
    "storage_bucket": "clubssocsdcu.appspot.com"
  },
  "client": [
    {
      "client_info": {
        "mobilesdk_app_id": "1:764934368349:android:a3a2296568f71861",
        "android_client_info": {
          "package_name": "com.clubsocapp"
        }
      },
      "oauth_client": [
        {
          "client_id": "764934368349-osst8i0gjjo59c35r3r79rl5ptj3kis8.apps.googleusercontent.com",
          "client_type": 3
        }
      ],
      "api_key": [
        {
          "current_key": "AIzaSyCYpv5Qk4J-x3hZ-OSW0lS2mw3Y0ay5ZBU"
        }
      ],
      "services": {
        "analytics_service": {
          "status": 1
        },
        "appinvite_service": {
          "status": 1,
          "other_platform_oauth_client": []
        },
        "ads_service": {
          "status": 2
        }
      }
    }
  ],
  "configuration_version": "1"
}